django_forge_ai/__init__.py
django_forge_ai/apps.py
django_forge_ai/models.py
django_forge_ai/settings.py
django_forge_ai/signals.py
django_forge_ai/tasks.py
django_forge_ai/admin_integration/__init__.py
django_forge_ai/admin_integration/apps.py
django_forge_ai/admin_integration/mixins.py
django_forge_ai/admin_integration/views.py
django_forge_ai/agents/__init__.py
django_forge_ai/agents/admin.py
django_forge_ai/agents/apps.py
django_forge_ai/agents/models.py
django_forge_ai/agents/orchestrator.py
django_forge_ai/rag_system/__init__.py
django_forge_ai/rag_system/admin.py
django_forge_ai/rag_system/apps.py
django_forge_ai/rag_system/mixins.py
django_forge_ai/rag_system/models.py
django_forge_ai/rag_system/vector_utils.py
django_forge_ai/utils/__init__.py
django_forge_ai/utils/llm_client.py
django_forge_ai/utils/validation.py
django_forge_ai-1.2.7.dist-info/licenses/LICENSE
django_forge_ai-1.2.7.dist-info/METADATA
django_forge_ai-1.2.7.dist-info/WHEEL
django_forge_ai-1.2.7.dist-info/top_level.txt
django_forge_ai-1.2.7.dist-info/RECORD
