Metadata-Version: 2.4
Name: django-forge-ai
Version: 1.2.7
Summary: A comprehensive AI toolbox for Django - seamless integration of LLM functionalities, RAG systems, and AI agents
Home-page: https://github.com/vortex-hue/django_forge_ai.git
Author: DjangoForgeAI Contributors
Author-email: DjangoForgeAI Contributors <your-email@example.com>
Maintainer-email: DjangoForgeAI Contributors <your-email@example.com>
License-Expression: MIT
Project-URL: Homepage, https://github.com/vortex-hue/django_forge_ai.git
Project-URL: Documentation, https://github.com/vortex-hue/django_forge_ai.git#readme
Project-URL: Repository, https://github.com/vortex-hue/django_forge_ai.git
Project-URL: Issues, https://github.com/vortex-hue/django_forge_ai.git/issues
Project-URL: Changelog, https://github.com/vortex-hue/django_forge_ai.git/blob/main/CHANGELOG.md
Keywords: django,ai,llm,rag,vector-database,openai,anthropic,machine-learning
Classifier: Development Status :: 3 - Alpha
Classifier: Intended Audience :: Developers
Classifier: Operating System :: OS Independent
Classifier: Programming Language :: Python :: 3
Classifier: Programming Language :: Python :: 3.8
Classifier: Programming Language :: Python :: 3.9
Classifier: Programming Language :: Python :: 3.10
Classifier: Programming Language :: Python :: 3.11
Classifier: Programming Language :: Python :: 3.12
Classifier: Framework :: Django
Classifier: Framework :: Django :: 3.2
Classifier: Framework :: Django :: 4.0
Classifier: Framework :: Django :: 4.1
Classifier: Framework :: Django :: 4.2
Classifier: Framework :: Django :: 5.0
Classifier: Topic :: Software Development :: Libraries :: Python Modules
Classifier: Topic :: Scientific/Engineering :: Artificial Intelligence
Requires-Python: >=3.8
License-File: LICENSE
Requires-Dist: django>=3.2
Requires-Dist: pydantic>=2.0.0
Requires-Dist: openai>=1.0.0
Requires-Dist: anthropic>=0.7.0
Requires-Dist: chromadb>=0.4.0
Requires-Dist: qdrant-client>=1.6.0
Requires-Dist: psycopg2-binary>=2.9.0
Requires-Dist: celery>=5.3.0
Requires-Dist: requests>=2.31.0
Requires-Dist: beautifulsoup4>=4.12.0
Requires-Dist: tiktoken>=0.5.0
Provides-Extra: dev
Requires-Dist: pytest>=7.4.0; extra == "dev"
Requires-Dist: pytest-django>=4.5.0; extra == "dev"
Requires-Dist: black>=23.0.0; extra == "dev"
Requires-Dist: flake8>=6.0.0; extra == "dev"
Requires-Dist: mypy>=1.5.0; extra == "dev"
Requires-Dist: coverage>=7.0.0; extra == "dev"
Dynamic: author
Dynamic: home-page
Dynamic: license-file
Dynamic: requires-python
